setup.py
Util/__init__.py
Util/database_helper.py
Util/e_mail.py
Util/excel.py
Util/file_helper.py
Util/ftp_helper.py
Util/id_number.py
Util/ssh_helper.py
autotest_helper.egg-info/PKG-INFO
autotest_helper.egg-info/SOURCES.txt
autotest_helper.egg-info/dependency_links.txt
autotest_helper.egg-info/requires.txt
autotest_helper.egg-info/top_level.txt
autotest_helper.egg-info/zip-safe